Metadata-Version: 2.1
Name: mosdex-python
Version: 2020.1.dev6
Summary: Package for running demo of MOSDEX modular optimization problem data standard
Home-page: https://github.com/coin-modeling-dev/mosdex-python/tree/2020.1.dev6
Author: Alan King
Author-email: kingaj@us.ibm.com
License: UNKNOWN
Platform: UNKNOWN
Classifier: Programming Language :: Python :: 3
Classifier: License :: OSI Approved :: MIT License
Classifier: Operating System :: OS Independent
Requires-Python: >=3.6
Provides-Extra: pg
Provides-Extra: pandas
Provides-Extra: redshift
